fashionsearch/__init__.py
fashionsearch/__main__.py
fashionsearch/feed.py
fashionsearch/viewer.py
fashionsearch-1.1.1.dist-info/LICENSE
fashionsearch-1.1.1.dist-info/METADATA
fashionsearch-1.1.1.dist-info/WHEEL
fashionsearch-1.1.1.dist-info/entry_points.txt
fashionsearch-1.1.1.dist-info/top_level.txt
fashionsearch-1.1.1.dist-info/RECORD
